downloader/__init__.py
downloader/downloader.py
downloader/elasticdownloader.py
downloader/test.py
downloader/elastic/__init__.py
downloader/elastic/ftp.py
downloader/elastic/sftp.py
downloader/helper/__init__.py
downloader/helper/hasher.py
downloader/helper/http_download.py
downloader_light-0.0.2.dist-info/METADATA
downloader_light-0.0.2.dist-info/WHEEL
downloader_light-0.0.2.dist-info/top_level.txt
downloader_light-0.0.2.dist-info/RECORD
