Metadata-Version: 2.1
Name: downloader-light
Version: 0.0.2
Summary: Lightweight python package that allows the download of thousands of files concurrently.
Home-page: https://github.com/ibragim64/python-downloader-light
Author: Ibragim Abubakarov
Author-email: ibragim.ai95@gmail.com
Maintainer: Ibragim Abubakarov
Maintainer-email: ibragim.ai95@gmail.com
License: UNKNOWN
Platform: UNKNOWN
Classifier: Programming Language :: Python :: 3
Classifier: Operating System :: OS Independent
Classifier: Intended Audience :: Developers
Classifier: Topic :: Internet :: WWW/HTTP
Classifier: Topic :: Internet :: File Transfer Protocol (FTP)
Requires-Dist: pysftp
Requires-Dist: requests
